meridian/__init__.py
meridian/__version__.py
meridian/spatialdataset.py
test/__init__.py
test/conftest.py
test/test_spatialdata.py
test/test_spatialdataset.py
meridian-1.1.0.dist-info/LICENSE
meridian-1.1.0.dist-info/METADATA
meridian-1.1.0.dist-info/WHEEL
meridian-1.1.0.dist-info/top_level.txt
meridian-1.1.0.dist-info/RECORD
