Metadata-Version: 2.1
Name: meridian
Version: 1.1.0
Summary: Easy geospatial data processing.
Home-page: https://github.com/tomplex/meridian
Author: Tom Caruso
Author-email: carusot42@gmail.com
License: MIT
Platform: UNKNOWN
Classifier: License :: OSI Approved :: MIT License
Classifier: Programming Language :: Python
Classifier: Programming Language :: Python :: 3
Classifier: Programming Language :: Python :: 3.6
Classifier: Programming Language :: Python :: Implementation :: CPython
Requires-Python: >=3.6.0
Requires-Dist: shapely (>=1.6.4.post2)
Requires-Dist: Rtree (>=0.8.3)
